reg_analytics_client/LICENSE
reg_analytics_client/README.md
reg_analytics_client/VERSION
reg_analytics_client/__init__.py
reg_analytics_client/api.py
reg_analytics_client/data.py
reg_analytics_client/py.typed
reg_analytics_client-0.0.0.dist-info/METADATA
reg_analytics_client-0.0.0.dist-info/WHEEL
reg_analytics_client-0.0.0.dist-info/top_level.txt
reg_analytics_client-0.0.0.dist-info/RECORD
