Metadata-Version: 2.1
Name: reg-analytics-client
Version: 0.0.0
Summary: reg-analytics-client
Author-email: belegnar <belegnar@belegnar.ru>
License: MIT License
Project-URL: Homepage, https://reg.konvent.ru
Classifier: License :: OSI Approved :: MIT License
Classifier: Intended Audience :: Developers
Classifier: Programming Language :: Python :: 3
Classifier: Programming Language :: Python :: 3 :: Only
Classifier: Programming Language :: Python :: 3.11
Classifier: Programming Language :: Python :: 3.12
Classifier: Operating System :: OS Independent
Classifier: Development Status :: 5 - Production/Stable
Requires-Python: >=3.11
Requires-Dist: httpx >=0.27.0
Requires-Dist: marshmallow-recipe >=0.0.39
